keyword_extraction/__init__.py
keyword_extraction/rank.py
keyword_extraction/regex.py
keyword_extraction/tfidf.py
keyword_extraction/tokenizer.py
keyword_extraction/w2v.py
keyword_extraction-0.0.3.dist-info/METADATA
keyword_extraction-0.0.3.dist-info/WHEEL
keyword_extraction-0.0.3.dist-info/top_level.txt
keyword_extraction-0.0.3.dist-info/RECORD
